kr8s/__init__.py
kr8s/_api.py
kr8s/_async_utils.py
kr8s/_auth.py
kr8s/_config.py
kr8s/_constants.py
kr8s/_data_utils.py
kr8s/_exceptions.py
kr8s/_exec.py
kr8s/_objects.py
kr8s/_portforward.py
kr8s/_testutils.py
kr8s/_types.py
kr8s/_version.py
kr8s/conftest.py
kr8s/objects.py
kr8s/portforward.py
kr8s/py.typed
kr8s/_vendored/asyncache/LICENSE
kr8s/_vendored/asyncache/__init__.py
kr8s/_vendored/asyncache/tests/test_asyncache_cached.py
kr8s/_vendored/asyncache/tests/test_asyncache_cachedmethod.py
kr8s/asyncio/__init__.py
kr8s/asyncio/_api.py
kr8s/asyncio/_helpers.py
kr8s/asyncio/objects.py
kr8s/asyncio/portforward.py
kr8s/tests/test_api.py
kr8s/tests/test_auth.py
kr8s/tests/test_config.py
kr8s/tests/test_data_utils.py
kr8s/tests/test_gen.py
kr8s/tests/test_io.py
kr8s/tests/test_objects.py
kr8s/tests/test_testutils.py
kr8s/tests/resources/configmap.yaml
kr8s/tests/resources/secret.yaml
kr8s/tests/resources/serviceaccount.yaml
kr8s/tests/resources/custom/evc.yaml
kr8s/tests/resources/simple/nginx_pod.yaml
kr8s/tests/resources/simple/nginx_pod_service.yaml
kr8s/tests/resources/simple/nested/nginx_ingress.yaml
kr8s/tests/scripts/envexec.py
kr8s-0.20.12.dist-info/METADATA
kr8s-0.20.12.dist-info/WHEEL
kr8s-0.20.12.dist-info/licenses/LICENSE
kr8s-0.20.12.dist-info/licenses/LICENSE_HEADER
kr8s-0.20.12.dist-info/RECORD
