Metadata-Version: 2.4
Name: kr8s
Version: 0.20.12
Summary: A Kubernetes API library
Project-URL: Documentation, https://docs.kr8s.org/en/stable
Project-URL: Repository, https://github.com/kr8s-org/kr8s.git
Project-URL: Issues, https://github.com/kr8s-org/kr8s/issues
Project-URL: Changelog, https://github.com/kr8s-org/kr8s/releases
Author-email: Jacob Tomlimson <jacob@tomlinson.email>
License: BSD-3-Clause
License-File: LICENSE
License-File: LICENSE_HEADER
Keywords: kubectl,kubernetes
Classifier: Programming Language :: Python :: 3
Requires-Python: >=3.9
Requires-Dist: anyio>=3.7.0
Requires-Dist: cachetools>=5.2.0
Requires-Dist: cryptography>=35
Requires-Dist: exceptiongroup>=1.2.0; python_version < '3.12'
Requires-Dist: httpx-ws>=0.7.0
Requires-Dist: httpx>=0.24.1
Requires-Dist: packaging>=23.0
Requires-Dist: python-box>=7.0.1
Requires-Dist: python-jsonpath>=0.7.1
Requires-Dist: pyyaml>=6.0
Requires-Dist: typing-extensions>=4.12.2; python_version < '3.12'
